LICENSE
MANIFEST.in
README.md
lc-drivers-list
lc-image-list
lc-node-add
lc-node-do
lc-node-list
lc-sizes-list
setup.py
lctools/__init__.py
lctools/config.py
lctools/lc.py
lctools/printer.py
lctools/shortcuts.py
lctools.egg-info/PKG-INFO
lctools.egg-info/SOURCES.txt
lctools.egg-info/dependency_links.txt
lctools.egg-info/top_level.txt