Metadata-Version: 1.0
Name: lctools
Version: 0.1.2
Summary: CLI tools for managing clouds, based on libcloud
Home-page: http://github.com/novel/lc-tools
Author: Roman Bogorodskiy
Author-email: bogorodskiy@gmail.com
License: Apache License (2.0)
Platform: UNKNOWN
Classifier: Development Status :: 3 - Alpha
Classifier: Environment :: Console
Classifier: Intended Audience :: System Administrators
Classifier: License :: OSI Approved :: Apache Software License
Classifier: Operating System :: OS Independent
Classifier: Programming Language :: Python
Classifier: Topic :: System
